<?xml version="1.0" encoding="UTF-8"?>
<beans xmlns="http://www.springframework.org/schema/beans"
       xmlns:xsi="http://www.w3.org/2001/XMLSchema-instance"
       xmlns:context="http://www.springframework.org/schema/context"
       xmlns:jpa="http://www.springframework.org/schema/data/jpa"
       xsi:schemaLocation="http://www.springframework.org/schema/beans
       http://www.springframework.org/schema/beans/spring-beans.xsd
       http://www.springframework.org/schema/context
       http://www.springframework.org/schema/context/spring-context.xsd
       http://www.springframework.org/schema/data/jpa
       http://www.springframework.org/schema/data/jpa/spring-jpa.xsd">

    <!--Поддержка автоматического связывания посредством аннотаций, но необходимо создавать бины для компонентов отдельно-->
    <!--<context:annotation-config/>-->

    <!--Поддержка автоматического связывания и создания компонентов на основе аннотаций-->
    <context:component-scan base-package="ru.leather.onlineshop"/>

    <!--Нужен для хранения интерфейсов репозетария JPA -->
    <jpa:repositories base-package="ru.leather.onlineshop.repository"/>

    <!-- EntityManagerFactory для связи с базой данных -->
    <bean id="emf" class="org.springframework.orm.jpa.LocalContainerEntityManagerFactoryBean">
        <property name="dataSource" ref="dataSource" />
        <!--Поставщик данных - hibernate-->
        <property name="jpaVendorAdapter">
            <bean class="org.springframework.orm.jpa.vendor.HibernateJpaVendorAdapter" />
        </property>
        <!--поиск сущностей в этом пакете-->
        <property name="packagesToScan"
                  value="ru.leather.onlineshop"/>
    </bean>

    <!-- Datasource. Источник данных - база MySQL -->
    <bean id="dataSource" class="org.springframework.jdbc.datasource.DriverManagerDataSource">
        <property name="driverClassName" value="com.mysql.jdbc.Driver" />
        <property name="url" value="jdbc:mysql://localhost:3306/onshope" />
        <property name="username" value="root" />
        <property name="password" value="root" />
    </bean>



</beans>